{
    "name": "auto_GB_glassesdirect.co.uk_bt9",
    "cosmetic": false,
    "_metadata": {
        "vendorUrl": "http://www.glassesdirect.co.uk/"
    },
    "runContext": {
        "main": true,
        "frame": false,
        "urlPattern": "^https?://(www\\.)?glassesdirect\\.co\\.uk/"
    },
    "prehideSelectors": ["div.cookie-banner_policy-buttons__TCti_"],
    "detectCmp": [
        {
            "exists": "div.cookie-banner_policy-buttons__TCti_"
        }
    ],
    "detectPopup": [
        {
            "visible": "div.cookie-banner_policy-buttons__TCti_"
        }
    ],
    "optIn": [
        {
            "waitForThenClick": "button.cookie-banner_cookie-cookie-accept__jLVGH"
        }
    ],
    "optOut": [
        {
            "waitForThenClick": "button.cookie-banner_btn-cookie-refuse__bVxnG"
        }
    ]
}
