{
    "name": "auto_DE_geero.de_ztz",
    "cosmetic": false,
    "_metadata": {
        "vendorUrl": "http://www.geero.de/"
    },
    "runContext": {
        "main": true,
        "frame": false,
        "urlPattern": "^https?://(www\\.)?geero\\.de/"
    },
    "prehideSelectors": [],
    "detectCmp": [
        {
            "exists": "body > div:not([id]) > form:nth-child(1):not([id]) > div:nth-child(3):not([id]) > button:nth-child(2):not([id])"
        }
    ],
    "detectPopup": [
        {
            "visible": "body > div:not([id]) > form:nth-child(1):not([id]) > div:nth-child(3):not([id]) > button:nth-child(2):not([id])"
        }
    ],
    "optIn": [],
    "optOut": [
        {
            "wait": 500
        },
        {
            "waitForThenClick": "body > div:not([id]) > form:nth-child(1):not([id]) > div:nth-child(3):not([id]) > button:nth-child(2):not([id])",
            "comment": "Nur erforderliche"
        }
    ],
    "test": [
        {
            "waitForVisible": "body > div:not([id]) > form:nth-child(1):not([id]) > div:nth-child(3):not([id]) > button:nth-child(2):not([id])",
            "timeout": 1000,
            "check": "none"
        }
    ]
}
