{
    "name": "auto_FR_cinememoire.net_hyq",
    "cosmetic": false,
    "_metadata": {
        "vendorUrl": "http://cinememoire.net/"
    },
    "runContext": {
        "main": true,
        "frame": false,
        "urlPattern": "^https?://(www\\.)?cinememoire\\.net/"
    },
    "prehideSelectors": [],
    "detectCmp": [
        {
            "exists": "body > div:not([id]) > div#glowCookies-banner > div:nth-child(3):not([id]) > button:nth-child(2)#rejectCookies"
        }
    ],
    "detectPopup": [
        {
            "visible": "body > div:not([id]) > div#glowCookies-banner > div:nth-child(3):not([id]) > button:nth-child(2)#rejectCookies"
        }
    ],
    "optIn": [],
    "optOut": [
        {
            "wait": 500
        },
        {
            "waitForThenClick": "body > div:not([id]) > div#glowCookies-banner > div:nth-child(3):not([id]) > button:nth-child(2)#rejectCookies",
            "comment": "Refuser"
        }
    ],
    "test": [
        {
            "waitForVisible": "body > div:not([id]) > div#glowCookies-banner > div:nth-child(3):not([id]) > button:nth-child(2)#rejectCookies",
            "timeout": 1000,
            "check": "none"
        }
    ]
}
