{
    "name": "auto_FR_sede.sepe.gob.es_nyh",
    "cosmetic": false,
    "_metadata": {
        "vendorUrl": "http://sede.sepe.gob.es/"
    },
    "runContext": {
        "main": true,
        "frame": false,
        "urlPattern": "^https?://(www\\.)?sede\\.sepe\\.gob\\.es/"
    },
    "prehideSelectors": [],
    "detectCmp": [
        {
            "exists": "body > div:not([id]) > div:not([id]) > button:nth-child(3):not([id])"
        }
    ],
    "detectPopup": [
        {
            "visible": "body > div:not([id]) > div:not([id]) > button:nth-child(3):not([id])"
        }
    ],
    "optIn": [],
    "optOut": [
        {
            "wait": 500
        },
        {
            "waitForThenClick": "body > div:not([id]) > div:not([id]) > button:nth-child(3):not([id])",
            "comment": "Rechazar todas"
        }
    ],
    "test": [
        {
            "waitForVisible": "body > div:not([id]) > div:not([id]) > button:nth-child(3):not([id])",
            "timeout": 1000,
            "check": "none"
        }
    ]
}
