{
    "name": "auto_CH_museicapitolini.org_gyo",
    "cosmetic": false,
    "_metadata": {
        "vendorUrl": "http://www.museicapitolini.org/"
    },
    "runContext": {
        "main": true,
        "frame": false,
        "urlPattern": "^https?://(www\\.)?museicapitolini\\.org/"
    },
    "prehideSelectors": [],
    "detectCmp": [
        {
            "exists": "body > div#sliding-popup > div:nth-child(2):not([id]) > div:not([id]) > div:nth-child(3)#popup-buttons > button:nth-child(3):not([id])"
        }
    ],
    "detectPopup": [
        {
            "visible": "body > div#sliding-popup > div:nth-child(2):not([id]) > div:not([id]) > div:nth-child(3)#popup-buttons > button:nth-child(3):not([id])"
        }
    ],
    "optIn": [],
    "optOut": [
        {
            "wait": 500
        },
        {
            "waitForThenClick": "body > div#sliding-popup > div:nth-child(2):not([id]) > div:not([id]) > div:nth-child(3)#popup-buttons > button:nth-child(3):not([id])",
            "comment": "Rifiuta tutti"
        }
    ],
    "test": [
        {
            "waitForVisible": "body > div#sliding-popup > div:nth-child(2):not([id]) > div:not([id]) > div:nth-child(3)#popup-buttons > button:nth-child(3):not([id])",
            "timeout": 1000,
            "check": "none"
        }
    ]
}
